kPOD/__init__.py
kPOD/examples.py
kPOD/initial_helpers.py
kPOD/kpod_implementation.py
kPOD/utils.py
kPOD-0.18.dist-info/LICENSE.md
kPOD-0.18.dist-info/METADATA
kPOD-0.18.dist-info/WHEEL
kPOD-0.18.dist-info/top_level.txt
kPOD-0.18.dist-info/RECORD
